Metadata-Version: 1.0
Name: fem-probability
Version: 0.1
Summary: Gaussian and binomial distributions
Home-page: UNKNOWN
Author: Femi Tofade
Author-email: tolatof@gmail.com
License: UNKNOWN
Platform: UNKNOWN
